serpy/__init__.py
serpy/fields.py
serpy/serializer.py
serpy-0.3.0.dist-info/DESCRIPTION.rst
serpy-0.3.0.dist-info/METADATA
serpy-0.3.0.dist-info/RECORD
serpy-0.3.0.dist-info/WHEEL
serpy-0.3.0.dist-info/metadata.json
serpy-0.3.0.dist-info/pbr.json
serpy-0.3.0.dist-info/top_level.txt
