Metadata-Version: 2.0
Name: serpy
Version: 0.3.0
Summary: ridiculously fast object serialization
Home-page: https://github.com/clarkduvall/serpy
Author: Clark DuVall
Author-email: clark.duvall@gmail.com
License: MIT
Keywords: serialization,rest,json,api,marshal,marshalling,validation,schema,fast
Platform: UNKNOWN
Classifier: Development Status :: 4 - Beta
Classifier: Intended Audience :: Developers
Classifier: License :: OSI Approved :: MIT License
Classifier: Programming Language :: Python :: 2
Classifier: Programming Language :: Python :: 2.7
Classifier: Programming Language :: Python :: 3
Classifier: Programming Language :: Python :: 3.3
Classifier: Programming Language :: Python :: 3.4
Classifier: Programming Language :: Python :: 3.5
Classifier: Programming Language :: Python :: 3.6
Classifier: Programming Language :: Python :: Implementation :: CPython
Classifier: Programming Language :: Python :: Implementation :: PyPy
Requires-Dist: six
